lumipy/__init__.py
lumipy/_config_manager.py
lumipy/client.py
lumipy/common.py
lumipy/query_job.py
lumipy/cli/__init__.py
lumipy/cli/app.py
lumipy/cli/commands/__init__.py
lumipy/cli/commands/config.py
lumipy/cli/commands/query.py
lumipy/cli/commands/run.py
lumipy/cli/commands/setup.py
lumipy/cli/commands/test.py
lumipy/helpers/__init__.py
lumipy/helpers/backoff_handler.py
lumipy/lumiflex/__init__.py
lumipy/lumiflex/column.py
lumipy/lumiflex/table.py
lumipy/lumiflex/utility_functions.py
lumipy/lumiflex/window.py
lumipy/lumiflex/_atlas/__init__.py
lumipy/lumiflex/_atlas/atlas.py
lumipy/lumiflex/_atlas/metafactory.py
lumipy/lumiflex/_atlas/query.py
lumipy/lumiflex/_atlas/utils.py
lumipy/lumiflex/_atlas/widgets.py
lumipy/lumiflex/_column/__init__.py
lumipy/lumiflex/_column/case.py
lumipy/lumiflex/_column/make.py
lumipy/lumiflex/_column/ordering.py
lumipy/lumiflex/_column/widgets.py
lumipy/lumiflex/_column/accessors/__init__.py
lumipy/lumiflex/_column/accessors/base_fn_accessor.py
lumipy/lumiflex/_column/accessors/cume_fn_accessor.py
lumipy/lumiflex/_column/accessors/dt_fn_accessor.py
lumipy/lumiflex/_column/accessors/finance_fn_accessor.py
lumipy/lumiflex/_column/accessors/json_fn_accessor.py
lumipy/lumiflex/_column/accessors/linreg_fn_accessor.py
lumipy/lumiflex/_column/accessors/metric_fn_accessor.py
lumipy/lumiflex/_column/accessors/stats_fn_accessor.py
lumipy/lumiflex/_column/accessors/str_fn_accessor.py
lumipy/lumiflex/_common/__init__.py
lumipy/lumiflex/_common/node.py
lumipy/lumiflex/_common/str_utils.py
lumipy/lumiflex/_common/widgets.py
lumipy/lumiflex/_metadata/__init__.py
lumipy/lumiflex/_metadata/dtype.py
lumipy/lumiflex/_metadata/field.py
lumipy/lumiflex/_metadata/table.py
lumipy/lumiflex/_metadata/var_name.py
lumipy/lumiflex/_metadata/widgets.py
lumipy/lumiflex/_method_tools/__init__.py
lumipy/lumiflex/_method_tools/constraints.py
lumipy/lumiflex/_method_tools/decorator.py
lumipy/lumiflex/_method_tools/method_tools.py
lumipy/lumiflex/_table/__init__.py
dve_lumipy_testing-1.0.546.dist-info/METADATA
dve_lumipy_testing-1.0.546.dist-info/WHEEL
dve_lumipy_testing-1.0.546.dist-info/entry_points.txt
dve_lumipy_testing-1.0.546.dist-info/top_level.txt
dve_lumipy_testing-1.0.546.dist-info/RECORD
